{
    "backend": "flask",
    "db_name": "",
    "db_pass": "",
    "db_type": "mysql",
    "db_user": "",
    "dbms": "1",
    "description": "generated product",
    "design": "datta-able",
    "docker": "0",
    "err_code": 0,
    "frontend": "",
    "heroku": "0",
    "pattern": "mvc",
    "pro": "0",
    "task_id": "331866f1-e2a5-433d-8bb1-31a6d42e942b",
    "task_info": "Upload Sources [0%] - 144 files",
    "task_output": "331866f1-e2a5-433d-8bb1-31a6d42e942b.zip",
    "task_result": "SUCCESS",
    "task_state": "RUNNING",
    "task_ts_end": "2024-01-15-06-54-39",
    "task_ts_start": "2024-01-15-06-54-38"
}